trojanzoo_sphinx_theme/__init__.py
trojanzoo_sphinx_theme/breadcrumbs.html
trojanzoo_sphinx_theme/fonts.html
trojanzoo_sphinx_theme/footer.html
trojanzoo_sphinx_theme/layout.html
trojanzoo_sphinx_theme/linkcode.py
trojanzoo_sphinx_theme/search.html
trojanzoo_sphinx_theme/searchbox.html
trojanzoo_sphinx_theme/theme.conf
trojanzoo_sphinx_theme/version.py
trojanzoo_sphinx_theme/versions.html
trojanzoo_sphinx_theme/static/css/theme.css
trojanzoo_sphinx_theme/static/fonts/FontAwesome/fontawesome-webfont.eot
trojanzoo_sphinx_theme/static/fonts/FontAwesome/fontawesome-webfont.svg
trojanzoo_sphinx_theme/static/fonts/FontAwesome/fontawesome-webfont.ttf
trojanzoo_sphinx_theme/static/fonts/FontAwesome/fontawesome-webfont.woff
trojanzoo_sphinx_theme/static/fonts/FontAwesome/fontawesome-webfont.woff2
trojanzoo_sphinx_theme/static/fonts/FreightSans/freight-sans-bold-italic.woff
trojanzoo_sphinx_theme/static/fonts/FreightSans/freight-sans-bold-italic.woff2
trojanzoo_sphinx_theme/static/fonts/FreightSans/freight-sans-bold.woff
trojanzoo_sphinx_theme/static/fonts/FreightSans/freight-sans-bold.woff2
trojanzoo_sphinx_theme/static/fonts/FreightSans/freight-sans-book-italic.woff
trojanzoo_sphinx_theme/static/fonts/FreightSans/freight-sans-book-italic.woff2
trojanzoo_sphinx_theme/static/fonts/FreightSans/freight-sans-book.woff
trojanzoo_sphinx_theme/static/fonts/FreightSans/freight-sans-book.woff2
trojanzoo_sphinx_theme/static/fonts/FreightSans/freight-sans-light-italic.woff
trojanzoo_sphinx_theme/static/fonts/FreightSans/freight-sans-light-italic.woff2
trojanzoo_sphinx_theme/static/fonts/FreightSans/freight-sans-light.woff
trojanzoo_sphinx_theme/static/fonts/FreightSans/freight-sans-light.woff2
trojanzoo_sphinx_theme/static/fonts/FreightSans/freight-sans-medium-italic.woff
trojanzoo_sphinx_theme/static/fonts/FreightSans/freight-sans-medium-italic.woff2
trojanzoo_sphinx_theme/static/fonts/FreightSans/freight-sans-medium.woff
trojanzoo_sphinx_theme-1.0.3.dist-info/LICENSE
trojanzoo_sphinx_theme-1.0.3.dist-info/METADATA
trojanzoo_sphinx_theme-1.0.3.dist-info/WHEEL
trojanzoo_sphinx_theme-1.0.3.dist-info/entry_points.txt
trojanzoo_sphinx_theme-1.0.3.dist-info/top_level.txt
trojanzoo_sphinx_theme-1.0.3.dist-info/RECORD
